shapeshifter_uftp/__init__.py
shapeshifter_uftp/cli.py
shapeshifter_uftp/exceptions.py
shapeshifter_uftp/logging.py
shapeshifter_uftp/oauth.py
shapeshifter_uftp/transport.py
shapeshifter_uftp/client/__init__.py
shapeshifter_uftp/client/agr_cro_client.py
shapeshifter_uftp/client/agr_dso_client.py
shapeshifter_uftp/client/base_client.py
shapeshifter_uftp/client/cro_agr_client.py
shapeshifter_uftp/client/cro_dso_client.py
shapeshifter_uftp/client/dso_agr_client.py
shapeshifter_uftp/client/dso_cro_client.py
shapeshifter_uftp/service/__init__.py
shapeshifter_uftp/service/agr_service.py
shapeshifter_uftp/service/base_service.py
shapeshifter_uftp/service/cro_service.py
shapeshifter_uftp/service/dso_service.py
shapeshifter_uftp/uftp/__init__.py
shapeshifter_uftp/uftp/agr_cro.py
shapeshifter_uftp/uftp/agr_dso.py
shapeshifter_uftp/uftp/common.py
shapeshifter_uftp/uftp/cro_dso.py
shapeshifter_uftp/uftp/defaults.py
shapeshifter_uftp/uftp/enums.py
shapeshifter_uftp/uftp/validations.py
shapeshifter_uftp/uftp/messages/__init__.py
shapeshifter_uftp/uftp/messages/agr_portfolio_query.py
shapeshifter_uftp/uftp/messages/agr_portfolio_update.py
shapeshifter_uftp/uftp/messages/d_prognosis.py
shapeshifter_uftp/uftp/messages/dso_portfolio_query.py
shapeshifter_uftp/uftp/messages/dso_portfolio_update.py
shapeshifter_uftp/uftp/messages/flex_message.py
shapeshifter_uftp/uftp/messages/flex_offer.py
shapeshifter_uftp/uftp/messages/flex_offer_revocation.py
shapeshifter_uftp/uftp/messages/flex_order.py
shapeshifter_uftp/uftp/messages/flex_request.py
shapeshifter_uftp/uftp/messages/flex_reservation_update.py
shapeshifter_uftp/uftp/messages/flex_settlement.py
shapeshifter_uftp/uftp/messages/metering.py
shapeshifter_uftp/uftp/messages/payload_message.py
shapeshifter_uftp/uftp/messages/signed_message.py
shapeshifter_uftp/uftp/messages/test_message.py
shapeshifter_uftp-2.1.1.dist-info/METADATA
shapeshifter_uftp-2.1.1.dist-info/WHEEL
shapeshifter_uftp-2.1.1.dist-info/entry_points.txt
shapeshifter_uftp-2.1.1.dist-info/top_level.txt
shapeshifter_uftp-2.1.1.dist-info/RECORD
