Metadata-Version: 2.4
Name: shapeshifter_uftp
Version: 2.1.1
Summary: Implementation of the Shapeshifter (UFTP) protocol
Project-URL: Repository, https://github.com/shapeshifter/shapeshifter-library-python
Project-URL: Documentation, https://github.com/shapeshifter/shapeshifter-library-python/README.md
Project-URL: Issues, https://github.com/shapeshifter/shapeshifter-library-python/issues
Project-URL: Changelog, https://github.com/shapeshifter/shapeshifter-library-python/blob/main/CHANGELOG.md
Requires-Python: >=3.11
Requires-Dist: xsdata[lxml]<26.0,>=25.0
Requires-Dist: pynacl==1.5.0
Requires-Dist: dnspython==2.7.0
Requires-Dist: fastapi<0.117,>=0.110
Requires-Dist: fastapi-xml<2.0.0,>=1.1.1
Requires-Dist: requests
Requires-Dist: uvicorn
Requires-Dist: termcolor
